investment_tracker/__init__.py
investment_tracker/cli.py
investment_tracker/exceptions.py
investment_tracker/investment_tracker.py
investment_tracker/models.py
investment_tracker-0.1.0.dist-info/AUTHORS.rst
investment_tracker-0.1.0.dist-info/LICENSE
investment_tracker-0.1.0.dist-info/METADATA
investment_tracker-0.1.0.dist-info/WHEEL
investment_tracker-0.1.0.dist-info/entry_points.txt
investment_tracker-0.1.0.dist-info/top_level.txt
investment_tracker-0.1.0.dist-info/RECORD
