Metadata-Version: 2.1
Name: investment-tracker
Version: 0.1.0
Summary: Tracks investments by pulling investment data from the web and storing your transaction data locally on your machine.
Home-page: https://github.com/rankoliang/investment_tracker
Author: Ranko Liang
Author-email: rankoliang@gmail.com
License: MIT license
Keywords: investment_tracker
Platform: UNKNOWN
Classifier: Development Status :: 2 - Pre-Alpha
Classifier: Intended Audience :: Developers
Classifier: License :: OSI Approved :: MIT License
Classifier: Natural Language :: English
Classifier: Programming Language :: Python :: 3
Classifier: Programming Language :: Python :: 3.6
Classifier: Programming Language :: Python :: 3.7
Classifier: Programming Language :: Python :: 3.8
Requires-Python: >=3.6
Requires-Dist: Click (>=7.0)
